hekatomb/__init__.py
hekatomb/ad_ldap.py
hekatomb/blobs.py
hekatomb/hekatomb.py
hekatomb-1.5.14.dist-info/LICENSE.md
hekatomb-1.5.14.dist-info/METADATA
hekatomb-1.5.14.dist-info/WHEEL
hekatomb-1.5.14.dist-info/entry_points.txt
hekatomb-1.5.14.dist-info/RECORD
