Metadata-Version: 2.1
Name: hekatomb
Version: 1.5.14
Summary: Python library to extract and decrypt all credentials from all domain computers
Home-page: https://github.com/ProcessusT/HEKATOMB
License: GPL-3.0-only
Keywords: hekatomb,dpapi,windows,blob,masterkey,activedirectory,credentials
Author: Processus Thief
Author-email: hekatomb@thiefin.fr
Maintainer: Processus Thief
Maintainer-email: hekatomb@thiefin.fr
Requires-Python: >=3.7,<4.0
Classifier: License :: OSI Approved :: GNU General Public License v3 (GPLv3)
Classifier: Programming Language :: Python :: 3
Classifier: Programming Language :: Python :: 3.7
Classifier: Programming Language :: Python :: 3.8
Classifier: Programming Language :: Python :: 3.9
Classifier: Programming Language :: Python :: 3.10
Classifier: Programming Language :: Python :: 3.11
Classifier: Programming Language :: Python :: 3.12
Classifier: Topic :: System :: Systems Administration :: Authentication/Directory
Classifier: Topic :: System :: Systems Administration :: Authentication/Directory :: LDAP
Requires-Dist: chardet (>=5.2.0,<6.0.0)
Requires-Dist: dnspython (>=2.2.1,<3.0.0)
Requires-Dist: impacket (>=0.10.0,<0.11.0)
Requires-Dist: ldap3 (>=2.9,<3.0)
Requires-Dist: pycryptodomex (>=3.15.0,<4.0.0)
Project-URL: Bug Tracker, https://github.com/ProcessusT/HEKATOMB/issues
Project-URL: Documentation, https://github.com/ProcessusT/HEKATOMB
Project-URL: Repository, https://github.com/ProcessusT/HEKATOMB
